{
  "main": {
    "id": "d32926c4cbfa0e4d",
    "type": "split",
    "children": [
      {
        "id": "13a5869d5ea760c9",
        "type": "tabs",
        "children": [
          {
            "id": "2737bde481fddc3c",
            "type": "leaf",
            "state": {
              "type": "markdown",
              "state": {
                "file": "Experiments1/Communication Experiments.md",
                "mode": "source",
                "source": false
              }
            }
          },
          {
            "id": "63ab278daf381751",
            "type": "leaf",
            "state": {
              "type": "markdown",
              "state": {
                "file": "Experiments1/Communication Experiments.md",
                "mode": "source",
                "source": false
              }
            }
          },
          {
            "id": "caef6a8cdef3e293",
            "type": "leaf",
            "state": {
              "type": "markdown",
              "state": {
                "file": "Experiments1/1.1 - Reset last fc layer of MNISTnet1.md",
                "mode": "source",
                "source": false
              }
            }
          },
          {
            "id": "399516e180c18917",
            "type": "leaf",
            "state": {
              "type": "markdown",
              "state": {
                "file": "Experiments1/1.2. - Reset all (two) fc layer of MNISTnet1.md",
                "mode": "source",
                "source": false
              }
            }
          }
        ],
        "currentTab": 3
      }
    ],
    "direction": "vertical"
  },
  "left": {
    "id": "9fae106d15eada13",
    "type": "split",
    "children": [
      {
        "id": "589559c77ca6d4b7",
        "type": "tabs",
        "children": [
          {
            "id": "148b83fbaa2858e3",
            "type": "leaf",
            "state": {
              "type": "file-explorer",
              "state": {
                "sortOrder": "alphabetical"
              }
            }
          },
          {
            "id": "bf6718dd1a5b730d",
            "type": "leaf",
            "state": {
              "type": "search",
              "state": {
                "query": "",
                "matchingCase": false,
                "explainSearch": false,
                "collapseAll": false,
                "extraContext": false,
                "sortOrder": "alphabetical"
              }
            }
          },
          {
            "id": "38ca31bd90efad8d",
            "type": "leaf",
            "state": {
              "type": "bookmarks",
              "state": {}
            }
          }
        ]
      }
    ],
    "direction": "horizontal",
    "width": 642.5
  },
  "right": {
    "id": "fc5bcbdb46e29a66",
    "type": "split",
    "children": [
      {
        "id": "a0b377e3078dc40f",
        "type": "tabs",
        "children": [
          {
            "id": "cb6ff051045659f5",
            "type": "leaf",
            "state": {
              "type": "backlink",
              "state": {
                "file": "Experiments1/1.2. - Reset all (two) fc layer of MNISTnet1.md",
                "collapseAll": false,
                "extraContext": false,
                "sortOrder": "alphabetical",
                "showSearch": false,
                "searchQuery": "",
                "backlinkCollapsed": false,
                "unlinkedCollapsed": true
              }
            }
          },
          {
            "id": "b89e88f630fba083",
            "type": "leaf",
            "state": {
              "type": "outgoing-link",
              "state": {
                "file": "Experiments1/1.2. - Reset all (two) fc layer of MNISTnet1.md",
                "linksCollapsed": false,
                "unlinkedCollapsed": true
              }
            }
          },
          {
            "id": "6e648d3497b8ce8d",
            "type": "leaf",
            "state": {
              "type": "tag",
              "state": {
                "sortOrder": "frequency",
                "useHierarchy": true
              }
            }
          },
          {
            "id": "873c38af263d6ce4",
            "type": "leaf",
            "state": {
              "type": "outline",
              "state": {
                "file": "Experiments1/1.2. - Reset all (two) fc layer of MNISTnet1.md"
              }
            }
          }
        ]
      }
    ],
    "direction": "horizontal",
    "width": 300,
    "collapsed": true
  },
  "left-ribbon": {
    "hiddenItems": {
      "switcher:Open quick switcher": false,
      "graph:Open graph view": false,
      "canvas:Create new canvas": false,
      "daily-notes:Open today's daily note": false,
      "templates:Insert template": false,
      "command-palette:Open command palette": false
    }
  },
  "active": "399516e180c18917",
  "lastOpenFiles": [
    "Pasted image 20240905203700.png",
    "Pasted image 20240905203617.png",
    "Experiments1/1.1 - Reset last fc layer of MNISTnet1.md",
    "Experiments1/1.2. - Reset all (two) fc layer of MNISTnet1.md",
    "Experiments1/tensorboards/experiment1.2/hparams.yaml",
    "Experiments1/tensorboards/experiment1.2/events.out.tfevents.1725553165.ip-10-192-10-202.5991.4",
    "Experiments1/tensorboards/experiment1.2/events.out.tfevents.1725552205.ip-10-192-10-202.5991.3",
    "Experiments1/tensorboards/experiment1.2/events.out.tfevents.1725552203.ip-10-192-10-202.5991.2",
    "Experiments1/tensorboards/experiment1.2",
    "Experiments1/tensorboards/experiment1.2-tensorboard-event/hparams.yaml",
    "Experiments1/tensorboards/experiment1.2-tensorboard-event/events.out.tfevents.1725553165.ip-10-192-10-202.5991.4",
    "Experiments1/tensorboards/experiment1.2-tensorboard-event/events.out.tfevents.1725552205.ip-10-192-10-202.5991.3",
    "Experiments1/tensorboards/experiment1.2-tensorboard-event/events.out.tfevents.1725552203.ip-10-192-10-202.5991.2",
    "Experiments1/tensorboards/experiment1.2-tensorboard-event",
    "Experiments1/Communication Experiments.md",
    "Experiments1/1.0 - Control.md",
    "ImageOpNet.png",
    "Experiments1/images/experiment1.1/Pasted image 20240905153004.png",
    "Related Work.md",
    "Experiments1/Pasted image 20240905130116.png",
    "Experiments1/Pasted image 20240905130300.png",
    "Main.md",
    "Pasted image 20240905121645.png",
    "Pasted image 20240905120912.png",
    "Pasted image 20240905014633.png",
    "Pasted image 20240905014607.png",
    "Pasted image 20240905014547.png"
  ]
}